confusion_visualization/__init__.py
confusion_visualization/confusion.py
confusion_visualization/demo.py
confusion_visualization/utils.py
confusion_visualization-1.0.dist-info/METADATA
confusion_visualization-1.0.dist-info/WHEEL
confusion_visualization-1.0.dist-info/licenses/LICENSE
confusion_visualization-1.0.dist-info/RECORD
