Metadata-Version: 2.3
Name: confusion-visualization
Version: 1.0
Project-URL: Homepage, https://github.com/suksia/confusion-visualization
Project-URL: Issues, https://github.com/suksia/confusion-visualization/issues
Author-email: Aiden Ochoa <aio5165@psu.edu>
License: MIT License
License-File: LICENSE
Classifier: Operating System :: OS Independent
Classifier: Programming Language :: Python :: 3
Requires-Dist: matplotlib>=3.9.1
Requires-Dist: opencv-python>=4.10.0.84
Requires-Dist: scikit-learn>=1.5.1
